Compiled from "OpenAiApi.java"
public class org.springframework.ai.openai.api.OpenAiApi {
  public static final org.springframework.ai.openai.api.OpenAiApi$ChatModel DEFAULT_CHAT_MODEL;

  public static final java.lang.String DEFAULT_EMBEDDING_MODEL;

  public org.springframework.ai.openai.api.OpenAiApi$Builder mutate();
    Code:
       0: new           #1                  // class org/springframework/ai/openai/api/OpenAiApi$Builder
       3: dup
       4: aload_0
       5: invokespecial #3                  // Method org/springframework/ai/openai/api/OpenAiApi$Builder."<init>":(Lorg/springframework/ai/openai/api/OpenAiApi;)V
       8: areturn

  public static org.springframework.ai.openai.api.OpenAiApi$Builder builder();
    Code:
       0: new           #1                  // class org/springframework/ai/openai/api/OpenAiApi$Builder
       3: dup
       4: invokespecial #7                  // Method org/springframework/ai/openai/api/OpenAiApi$Builder."<init>":()V
       7: areturn

  public org.springframework.ai.openai.api.OpenAiApi(java.lang.String, org.springframework.ai.model.ApiKey, org.springframework.util.MultiValueMap<java.lang.String, java.lang.String>, java.lang.String, java.lang.String, org.springframework.web.client.RestClient$Builder, org.springframework.web.reactive.function.client.WebClient$Builder, org.springframework.web.client.ResponseErrorHandler);
    Code:
       0: aload_0
       1: invokespecial #10                 // Method java/lang/Object."<init>":()V
       4: aload_0
       5: new           #13                 // class org/springframework/ai/openai/api/OpenAiStreamFunctionCallingHelper
       8: dup
       9: invokespecial #15                 // Method org/springframework/ai/openai/api/OpenAiStreamFunctionCallingHelper."<init>":()V
      12: putfield      #16                 // Field chunkMerger:Lorg/springframework/ai/openai/api/OpenAiStreamFunctionCallingHelper;
      15: aload_0
      16: aload_1
      17: putfield      #22                 // Field baseUrl:Ljava/lang/String;
      20: aload_0
      21: aload_2
      22: putfield      #26                 // Field apiKey:Lorg/springframework/ai/model/ApiKey;
      25: aload_0
      26: aload_3
      27: putfield      #30                 // Field headers:Lorg/springframework/util/MultiValueMap;
      30: aload_0
      31: aload         4
      33: putfield      #34                 // Field completionsPath:Ljava/lang/String;
      36: aload_0
      37: aload         5
      39: putfield      #37                 // Field embeddingsPath:Ljava/lang/String;
      42: aload_0
      43: aload         8
      45: putfield      #40                 // Field responseErrorHandler:Lorg/springframework/web/client/ResponseErrorHandler;
      48: aload         4
      50: ldc           #44                 // String Completions Path must not be null
      52: invokestatic  #46                 // Method org/springframework/util/Assert.hasText:(Ljava/lang/String;Ljava/lang/String;)V
      55: aload         5
      57: ldc           #52                 // String Embeddings Path must not be null
      59: invokestatic  #46                 // Method org/springframework/util/Assert.hasText:(Ljava/lang/String;Ljava/lang/String;)V
      62: aload_3
      63: ldc           #54                 // String Headers must not be null
      65: invokestatic  #56                 // Method org/springframework/util/Assert.notNull:(Ljava/lang/Object;Ljava/lang/String;)V
      68: aload_3
      69: invokedynamic #60,  0             // InvokeDynamic #0:accept:(Lorg/springframework/util/MultiValueMap;)Ljava/util/function/Consumer;
      74: astore        9
      76: aload_0
      77: aload         6
      79: invokeinterface #64,  1           // InterfaceMethod org/springframework/web/client/RestClient$Builder.clone:()Lorg/springframework/web/client/RestClient$Builder;
      84: aload_1
      85: invokeinterface #70,  2           // InterfaceMethod org/springframework/web/client/RestClient$Builder.baseUrl:(Ljava/lang/String;)Lorg/springframework/web/client/RestClient$Builder;
      90: aload         9
      92: invokeinterface #73,  2           // InterfaceMethod org/springframework/web/client/RestClient$Builder.defaultHeaders:(Ljava/util/function/Consumer;)Lorg/springframework/web/client/RestClient$Builder;
      97: aload         8
      99: invokeinterface #77,  2           // InterfaceMethod org/springframework/web/client/RestClient$Builder.defaultStatusHandler:(Lorg/springframework/web/client/ResponseErrorHandler;)Lorg/springframework/web/client/RestClient$Builder;
     104: invokeinterface #81,  1           // InterfaceMethod org/springframework/web/client/RestClient$Builder.build:()Lorg/springframework/web/client/RestClient;
     109: putfield      #85                 // Field restClient:Lorg/springframework/web/client/RestClient;
     112: aload_0
     113: aload         7
     115: invokeinterface #89,  1           // InterfaceMethod org/springframework/web/reactive/function/client/WebClient$Builder.clone:()Lorg/springframework/web/reactive/function/client/WebClient$Builder;
     120: aload_1
     121: invokeinterface #94,  2           // InterfaceMethod org/springframework/web/reactive/function/client/WebClient$Builder.baseUrl:(Ljava/lang/String;)Lorg/springframework/web/reactive/function/client/WebClient$Builder;
     126: aload         9
     128: invokeinterface #97,  2           // InterfaceMethod org/springframework/web/reactive/function/client/WebClient$Builder.defaultHeaders:(Ljava/util/function/Consumer;)Lorg/springframework/web/reactive/function/client/WebClient$Builder;
     133: invokeinterface #100,  1          // InterfaceMethod org/springframework/web/reactive/function/client/WebClient$Builder.build:()Lorg/springframework/web/reactive/function/client/WebClient;
     138: putfield      #103                // Field webClient:Lorg/springframework/web/reactive/function/client/WebClient;
     141: return

  public static java.lang.String getTextContent(java.util.List<org.springframework.ai.openai.api.OpenAiApi$ChatCompletionMessage$MediaContent>);
    Code:
       0: aload_0
       1: ldc           #107                // String content cannot be null
       3: invokestatic  #56                 // Method org/springframework/util/Assert.notNull:(Ljava/lang/Object;Ljava/lang/String;)V
       6: aload_0
       7: invokeinterface #109,  1          // InterfaceMethod java/util/List.stream:()Ljava/util/stream/Stream;
      12: invokedynamic #115,  0            // InvokeDynamic #1:test:()Ljava/util/function/Predicate;
      17: invokeinterface #119,  2          // InterfaceMethod java/util/stream/Stream.filter:(Ljava/util/function/Predicate;)Ljava/util/stream/Stream;
      22: invokedynamic #125,  0            // InvokeDynamic #2:apply:()Ljava/util/function/Function;
      27: invokeinterface #129,  2          // InterfaceMethod java/util/stream/Stream.map:(Ljava/util/function/Function;)Ljava/util/stream/Stream;
      32: invokestatic  #133                // Method java/util/stream/Collectors.joining:()Ljava/util/stream/Collector;
      35: invokeinterface #139,  2          // InterfaceMethod java/util/stream/Stream.collect:(Ljava/util/stream/Collector;)Ljava/lang/Object;
      40: checkcast     #143                // class java/lang/String
      43: areturn

  public org.springframework.http.ResponseEntity<org.springframework.ai.openai.api.OpenAiApi$ChatCompletion> chatCompletionEntity(org.springframework.ai.openai.api.OpenAiApi$ChatCompletionRequest);
    Code:
       0: aload_0
       1: aload_1
       2: new           #145                // class org/springframework/util/LinkedMultiValueMap
       5: dup
       6: invokespecial #147                // Method org/springframework/util/LinkedMultiValueMap."<init>":()V
       9: invokevirtual #148                // Method chatCompletionEntity:(Lorg/springframework/ai/openai/api/OpenAiApi$ChatCompletionRequest;Lorg/springframework/util/MultiValueMap;)Lorg/springframework/http/ResponseEntity;
      12: areturn

  public org.springframework.http.ResponseEntity<org.springframework.ai.openai.api.OpenAiApi$ChatCompletion> chatCompletionEntity(org.springframework.ai.openai.api.OpenAiApi$ChatCompletionRequest, org.springframework.util.MultiValueMap<java.lang.String, java.lang.String>);
    Code:
       0: aload_1
       1: ldc           #152                // String The request body can not be null.
       3: invokestatic  #56                 // Method org/springframework/util/Assert.notNull:(Ljava/lang/Object;Ljava/lang/String;)V
       6: aload_1
       7: invokevirtual #154                // Method org/springframework/ai/openai/api/OpenAiApi$ChatCompletionRequest.stream:()Ljava/lang/Boolean;
      10: invokevirtual #159                // Method java/lang/Boolean.booleanValue:()Z
      13: ifne          20
      16: iconst_1
      17: goto          21
      20: iconst_0
      21: ldc           #165                // String Request must set the stream property to false.
      23: invokestatic  #167                // Method org/springframework/util/Assert.isTrue:(ZLjava/lang/String;)V
      26: aload_2
      27: ldc           #171                // String The additional HTTP headers can not be null.
      29: invokestatic  #56                 // Method org/springframework/util/Assert.notNull:(Ljava/lang/Object;Ljava/lang/String;)V
      32: aload_0
      33: getfield      #85                 // Field restClient:Lorg/springframework/web/client/RestClient;
      36: invokeinterface #173,  1          // InterfaceMethod org/springframework/web/client/RestClient.post:()Lorg/springframework/web/client/RestClient$RequestBodyUriSpec;
      41: aload_0
      42: getfield      #34                 // Field completionsPath:Ljava/lang/String;
      45: iconst_0
      46: anewarray     #11                 // class java/lang/Object
      49: invokeinterface #179,  3          // InterfaceMethod org/springframework/web/client/RestClient$RequestBodyUriSpec.uri:(Ljava/lang/String;[Ljava/lang/Object;)Lorg/springframework/web/client/RestClient$RequestHeadersSpec;
      54: checkcast     #185                // class org/springframework/web/client/RestClient$RequestBodySpec
      57: aload_0
      58: aload_2
      59: invokedynamic #187,  0            // InvokeDynamic #3:accept:(Lorg/springframework/ai/openai/api/OpenAiApi;Lorg/springframework/util/MultiValueMap;)Ljava/util/function/Consumer;
      64: invokeinterface #190,  2          // InterfaceMethod org/springframework/web/client/RestClient$RequestBodySpec.headers:(Ljava/util/function/Consumer;)Lorg/springframework/web/client/RestClient$RequestHeadersSpec;
      69: checkcast     #185                // class org/springframework/web/client/RestClient$RequestBodySpec
      72: aload_1
      73: invokeinterface #193,  2          // InterfaceMethod org/springframework/web/client/RestClient$RequestBodySpec.body:(Ljava/lang/Object;)Lorg/springframework/web/client/RestClient$RequestBodySpec;
      78: invokeinterface #197,  1          // InterfaceMethod org/springframework/web/client/RestClient$RequestBodySpec.retrieve:()Lorg/springframework/web/client/RestClient$ResponseSpec;
      83: ldc           #201                // class org/springframework/ai/openai/api/OpenAiApi$ChatCompletion
      85: invokeinterface #203,  2          // InterfaceMethod org/springframework/web/client/RestClient$ResponseSpec.toEntity:(Ljava/lang/Class;)Lorg/springframework/http/ResponseEntity;
      90: areturn

  public reactor.core.publisher.Flux<org.springframework.ai.openai.api.OpenAiApi$ChatCompletionChunk> chatCompletionStream(org.springframework.ai.openai.api.OpenAiApi$ChatCompletionRequest);
    Code:
       0: aload_0
       1: aload_1
       2: new           #145                // class org/springframework/util/LinkedMultiValueMap
       5: dup
       6: invokespecial #147                // Method org/springframework/util/LinkedMultiValueMap."<init>":()V
       9: invokevirtual #209                // Method chatCompletionStream:(Lorg/springframework/ai/openai/api/OpenAiApi$ChatCompletionRequest;Lorg/springframework/util/MultiValueMap;)Lreactor/core/publisher/Flux;
      12: areturn

  public reactor.core.publisher.Flux<org.springframework.ai.openai.api.OpenAiApi$ChatCompletionChunk> chatCompletionStream(org.springframework.ai.openai.api.OpenAiApi$ChatCompletionRequest, org.springframework.util.MultiValueMap<java.lang.String, java.lang.String>);
    Code:
       0: aload_1
       1: ldc           #152                // String The request body can not be null.
       3: invokestatic  #56                 // Method org/springframework/util/Assert.notNull:(Ljava/lang/Object;Ljava/lang/String;)V
       6: aload_1
       7: invokevirtual #154                // Method org/springframework/ai/openai/api/OpenAiApi$ChatCompletionRequest.stream:()Ljava/lang/Boolean;
      10: invokevirtual #159                // Method java/lang/Boolean.booleanValue:()Z
      13: ldc           #213                // String Request must set the stream property to true.
      15: invokestatic  #167                // Method org/springframework/util/Assert.isTrue:(ZLjava/lang/String;)V
      18: new           #215                // class java/util/concurrent/atomic/AtomicBoolean
      21: dup
      22: iconst_0
      23: invokespecial #217                // Method java/util/concurrent/atomic/AtomicBoolean."<init>":(Z)V
      26: astore_3
      27: aload_0
      28: getfield      #103                // Field webClient:Lorg/springframework/web/reactive/function/client/WebClient;
      31: invokeinterface #220,  1          // InterfaceMethod org/springframework/web/reactive/function/client/WebClient.post:()Lorg/springframework/web/reactive/function/client/WebClient$RequestBodyUriSpec;
      36: aload_0
      37: getfield      #34                 // Field completionsPath:Ljava/lang/String;
      40: iconst_0
      41: anewarray     #11                 // class java/lang/Object
      44: invokeinterface #225,  3          // InterfaceMethod org/springframework/web/reactive/function/client/WebClient$RequestBodyUriSpec.uri:(Ljava/lang/String;[Ljava/lang/Object;)Lorg/springframework/web/reactive/function/client/WebClient$RequestHeadersSpec;
      49: checkcast     #230                // class org/springframework/web/reactive/function/client/WebClient$RequestBodySpec
      52: aload_0
      53: aload_2
      54: invokedynamic #232,  0            // InvokeDynamic #4:accept:(Lorg/springframework/ai/openai/api/OpenAiApi;Lorg/springframework/util/MultiValueMap;)Ljava/util/function/Consumer;
      59: invokeinterface #233,  2          // InterfaceMethod org/springframework/web/reactive/function/client/WebClient$RequestBodySpec.headers:(Ljava/util/function/Consumer;)Lorg/springframework/web/reactive/function/client/WebClient$RequestHeadersSpec;
      64: checkcast     #230                // class org/springframework/web/reactive/function/client/WebClient$RequestBodySpec
      67: aload_1
      68: invokestatic  #236                // Method reactor/core/publisher/Mono.just:(Ljava/lang/Object;)Lreactor/core/publisher/Mono;
      71: ldc           #155                // class org/springframework/ai/openai/api/OpenAiApi$ChatCompletionRequest
      73: invokeinterface #242,  3          // InterfaceMethod org/springframework/web/reactive/function/client/WebClient$RequestBodySpec.body:(Lorg/reactivestreams/Publisher;Ljava/lang/Class;)Lorg/springframework/web/reactive/function/client/WebClient$RequestHeadersSpec;
      78: invokeinterface #245,  1          // InterfaceMethod org/springframework/web/reactive/function/client/WebClient$RequestHeadersSpec.retrieve:()Lorg/springframework/web/reactive/function/client/WebClient$ResponseSpec;
      83: ldc           #143                // class java/lang/String
      85: invokeinterface #250,  2          // InterfaceMethod org/springframework/web/reactive/function/client/WebClient$ResponseSpec.bodyToFlux:(Ljava/lang/Class;)Lreactor/core/publisher/Flux;
      90: getstatic     #256                // Field SSE_DONE_PREDICATE:Ljava/util/function/Predicate;
      93: invokevirtual #260                // Method reactor/core/publisher/Flux.takeUntil:(Ljava/util/function/Predicate;)Lreactor/core/publisher/Flux;
      96: getstatic     #256                // Field SSE_DONE_PREDICATE:Ljava/util/function/Predicate;
      99: invokeinterface #266,  1          // InterfaceMethod java/util/function/Predicate.negate:()Ljava/util/function/Predicate;
     104: invokevirtual #271                // Method reactor/core/publisher/Flux.filter:(Ljava/util/function/Predicate;)Lreactor/core/publisher/Flux;
     107: invokedynamic #273,  0            // InvokeDynamic #5:apply:()Ljava/util/function/Function;
     112: invokevirtual #274                // Method reactor/core/publisher/Flux.map:(Ljava/util/function/Function;)Lreactor/core/publisher/Flux;
     115: aload_0
     116: aload_3
     117: invokedynamic #277,  0            // InvokeDynamic #6:apply:(Lorg/springframework/ai/openai/api/OpenAiApi;Ljava/util/concurrent/atomic/AtomicBoolean;)Ljava/util/function/Function;
     122: invokevirtual #274                // Method reactor/core/publisher/Flux.map:(Ljava/util/function/Function;)Lreactor/core/publisher/Flux;
     125: aload_0
     126: aload_3
     127: invokedynamic #280,  0            // InvokeDynamic #7:test:(Lorg/springframework/ai/openai/api/OpenAiApi;Ljava/util/concurrent/atomic/AtomicBoolean;)Ljava/util/function/Predicate;
     132: invokevirtual #283                // Method reactor/core/publisher/Flux.windowUntil:(Ljava/util/function/Predicate;)Lreactor/core/publisher/Flux;
     135: aload_0
     136: invokedynamic #286,  0            // InvokeDynamic #8:apply:(Lorg/springframework/ai/openai/api/OpenAiApi;)Ljava/util/function/Function;
     141: invokevirtual #289                // Method reactor/core/publisher/Flux.concatMapIterable:(Ljava/util/function/Function;)Lreactor/core/publisher/Flux;
     144: invokedynamic #292,  0            // InvokeDynamic #9:apply:()Ljava/util/function/Function;
     149: invokevirtual #293                // Method reactor/core/publisher/Flux.flatMap:(Ljava/util/function/Function;)Lreactor/core/publisher/Flux;
     152: areturn

  public <T> org.springframework.http.ResponseEntity<org.springframework.ai.openai.api.OpenAiApi$EmbeddingList<org.springframework.ai.openai.api.OpenAiApi$Embedding>> embeddings(org.springframework.ai.openai.api.OpenAiApi$EmbeddingRequest<T>);
    Code:
       0: aload_1
       1: ldc           #152                // String The request body can not be null.
       3: invokestatic  #56                 // Method org/springframework/util/Assert.notNull:(Ljava/lang/Object;Ljava/lang/String;)V
       6: aload_1
       7: invokevirtual #296                // Method org/springframework/ai/openai/api/OpenAiApi$EmbeddingRequest.input:()Ljava/lang/Object;
      10: ldc_w         #302                // String The input can not be null.
      13: invokestatic  #56                 // Method org/springframework/util/Assert.notNull:(Ljava/lang/Object;Ljava/lang/String;)V
      16: aload_1
      17: invokevirtual #296                // Method org/springframework/ai/openai/api/OpenAiApi$EmbeddingRequest.input:()Ljava/lang/Object;
      20: instanceof    #143                // class java/lang/String
      23: ifne          36
      26: aload_1
      27: invokevirtual #296                // Method org/springframework/ai/openai/api/OpenAiApi$EmbeddingRequest.input:()Ljava/lang/Object;
      30: instanceof    #110                // class java/util/List
      33: ifeq          40
      36: iconst_1
      37: goto          41
      40: iconst_0
      41: ldc_w         #304                // String The input must be either a String, or a List of Strings or List of List of integers.
      44: invokestatic  #167                // Method org/springframework/util/Assert.isTrue:(ZLjava/lang/String;)V
      47: aload_1
      48: invokevirtual #296                // Method org/springframework/ai/openai/api/OpenAiApi$EmbeddingRequest.input:()Ljava/lang/Object;
      51: astore_3
      52: aload_3
      53: instanceof    #110                // class java/util/List
      56: ifeq          155
      59: aload_3
      60: checkcast     #110                // class java/util/List
      63: astore_2
      64: aload_2
      65: invokestatic  #306                // Method org/springframework/util/CollectionUtils.isEmpty:(Ljava/util/Collection;)Z
      68: ifne          75
      71: iconst_1
      72: goto          76
      75: iconst_0
      76: ldc_w         #312                // String The input list can not be empty.
      79: invokestatic  #167                // Method org/springframework/util/Assert.isTrue:(ZLjava/lang/String;)V
      82: aload_2
      83: invokeinterface #314,  1          // InterfaceMethod java/util/List.size:()I
      88: sipush        2048
      91: if_icmpgt     98
      94: iconst_1
      95: goto          99
      98: iconst_0
      99: ldc_w         #318                // String The list must be 2048 dimensions or less
     102: invokestatic  #167                // Method org/springframework/util/Assert.isTrue:(ZLjava/lang/String;)V
     105: aload_2
     106: iconst_0
     107: invokeinterface #320,  2          // InterfaceMethod java/util/List.get:(I)Ljava/lang/Object;
     112: instanceof    #143                // class java/lang/String
     115: ifne          144
     118: aload_2
     119: iconst_0
     120: invokeinterface #320,  2          // InterfaceMethod java/util/List.get:(I)Ljava/lang/Object;
     125: instanceof    #324                // class java/lang/Integer
     128: ifne          144
     131: aload_2
     132: iconst_0
     133: invokeinterface #320,  2          // InterfaceMethod java/util/List.get:(I)Ljava/lang/Object;
     138: instanceof    #110                // class java/util/List
     141: ifeq          148
     144: iconst_1
     145: goto          149
     148: iconst_0
     149: ldc_w         #326                // String The input must be either a String, or a List of Strings or list of list of integers.
     152: invokestatic  #167                // Method org/springframework/util/Assert.isTrue:(ZLjava/lang/String;)V
     155: aload_0
     156: getfield      #85                 // Field restClient:Lorg/springframework/web/client/RestClient;
     159: invokeinterface #173,  1          // InterfaceMethod org/springframework/web/client/RestClient.post:()Lorg/springframework/web/client/RestClient$RequestBodyUriSpec;
     164: aload_0
     165: getfield      #37                 // Field embeddingsPath:Ljava/lang/String;
     168: iconst_0
     169: anewarray     #11                 // class java/lang/Object
     172: invokeinterface #179,  3          // InterfaceMethod org/springframework/web/client/RestClient$RequestBodyUriSpec.uri:(Ljava/lang/String;[Ljava/lang/Object;)Lorg/springframework/web/client/RestClient$RequestHeadersSpec;
     177: checkcast     #185                // class org/springframework/web/client/RestClient$RequestBodySpec
     180: aload_0
     181: invokedynamic #328,  0            // InvokeDynamic #10:accept:(Lorg/springframework/ai/openai/api/OpenAiApi;)Ljava/util/function/Consumer;
     186: invokeinterface #190,  2          // InterfaceMethod org/springframework/web/client/RestClient$RequestBodySpec.headers:(Ljava/util/function/Consumer;)Lorg/springframework/web/client/RestClient$RequestHeadersSpec;
     191: checkcast     #185                // class org/springframework/web/client/RestClient$RequestBodySpec
     194: aload_1
     195: invokeinterface #193,  2          // InterfaceMethod org/springframework/web/client/RestClient$RequestBodySpec.body:(Ljava/lang/Object;)Lorg/springframework/web/client/RestClient$RequestBodySpec;
     200: invokeinterface #197,  1          // InterfaceMethod org/springframework/web/client/RestClient$RequestBodySpec.retrieve:()Lorg/springframework/web/client/RestClient$ResponseSpec;
     205: new           #331                // class org/springframework/ai/openai/api/OpenAiApi$1
     208: dup
     209: aload_0
     210: invokespecial #333                // Method org/springframework/ai/openai/api/OpenAiApi$1."<init>":(Lorg/springframework/ai/openai/api/OpenAiApi;)V
     213: invokeinterface #334,  2          // InterfaceMethod org/springframework/web/client/RestClient$ResponseSpec.toEntity:(Lorg/springframework/core/ParameterizedTypeReference;)Lorg/springframework/http/ResponseEntity;
     218: areturn

  java.lang.String getBaseUrl();
    Code:
       0: aload_0
       1: getfield      #22                 // Field baseUrl:Ljava/lang/String;
       4: areturn

  org.springframework.ai.model.ApiKey getApiKey();
    Code:
       0: aload_0
       1: getfield      #26                 // Field apiKey:Lorg/springframework/ai/model/ApiKey;
       4: areturn

  org.springframework.util.MultiValueMap<java.lang.String, java.lang.String> getHeaders();
    Code:
       0: aload_0
       1: getfield      #30                 // Field headers:Lorg/springframework/util/MultiValueMap;
       4: areturn

  java.lang.String getCompletionsPath();
    Code:
       0: aload_0
       1: getfield      #34                 // Field completionsPath:Ljava/lang/String;
       4: areturn

  java.lang.String getEmbeddingsPath();
    Code:
       0: aload_0
       1: getfield      #37                 // Field embeddingsPath:Ljava/lang/String;
       4: areturn

  org.springframework.web.client.ResponseErrorHandler getResponseErrorHandler();
    Code:
       0: aload_0
       1: getfield      #40                 // Field responseErrorHandler:Lorg/springframework/web/client/ResponseErrorHandler;
       4: areturn

  static {};
    Code:
       0: getstatic     #423                // Field org/springframework/ai/openai/api/OpenAiApi$ChatModel.GPT_4_O:Lorg/springframework/ai/openai/api/OpenAiApi$ChatModel;
       3: putstatic     #429                // Field DEFAULT_CHAT_MODEL:Lorg/springframework/ai/openai/api/OpenAiApi$ChatModel;
       6: getstatic     #432                // Field org/springframework/ai/openai/api/OpenAiApi$EmbeddingModel.TEXT_EMBEDDING_ADA_002:Lorg/springframework/ai/openai/api/OpenAiApi$EmbeddingModel;
       9: invokevirtual #438                // Method org/springframework/ai/openai/api/OpenAiApi$EmbeddingModel.getValue:()Ljava/lang/String;
      12: putstatic     #439                // Field DEFAULT_EMBEDDING_MODEL:Ljava/lang/String;
      15: ldc_w         #442                // String [DONE]
      18: invokedynamic #444,  0            // InvokeDynamic #12:test:(Ljava/lang/String;)Ljava/util/function/Predicate;
      23: putstatic     #256                // Field SSE_DONE_PREDICATE:Ljava/util/function/Predicate;
      26: return
}
